[{"__type__":"cc.Prefab","_name":"SimulationInitializer_BigJackpot","data":{"__id__":1}},{"__type__":"cc.Node","_name":"SimulationInitializer_BigJackpot","_children":[{"__id__":2}],"_components":[{"__type__":"6db6c6oQSZPnoJaWm/yRoYN","node":{"__id__":1},"m_pBallSimulationScene":{"__id__":28}},{"__type__":"c268dEeKFVBbptAkVHVkylL","node":{"__id__":1}}],"_prefab":{"__type__":"cc.PrefabInfo","root":{"__id__":1},"asset":{"__uuid__":"2a9e77e9-5d90-4ae6-9186-44fcaaacb961"},"fileId":"43e2cI9Vb1I27S/mt8esiSN"}},{"__type__":"cc.Node","_name":"Simulation","_parent":{"__id__":1},"_children":[{"__id__":3},{"__id__":13}],"_position":{"__type__":"cc.Vec2","x":-360,"y":-640},"_components":[{"__id__":28}],"_prefab":{"__type__":"cc.PrefabInfo","root":{"__id__":1},"asset":{"__uuid__":"2a9e77e9-5d90-4ae6-9186-44fcaaacb961"},"fileId":"39ce0SiH8JDCba+kYFGecud"}},{"__type__":"cc.Node","_name":"Jackpot Scene","_parent":{"__id__":2},"_children":[{"__id__":4},{"__id__":7},{"__id__":8},{"__id__":10}],"_scaleX":0.64,"_scaleY":0.64,"_position":{"__type__":"cc.Vec2","x":360,"y":736},"_prefab":{"__type__":"cc.PrefabInfo","root":{"__id__":1},"asset":{"__uuid__":"2a9e77e9-5d90-4ae6-9186-44fcaaacb961"},"fileId":"988b1ThJTxIYKoHWuduaXi4"}},{"__type__":"cc.Node","_name":"BtnSpin","_parent":{"__id__":3},"_contentSize":{"__type__":"cc.Size","width":323,"height":294},"_children":[{"__id__":5}],"_scaleX":1.5037594,"_scaleY":1.5037594,"_position":{"__type__":"cc.Vec2","y":-802},"_components":[{"__type__":"cc.Sprite","node":{"__id__":4},"_spriteFrame":{"__uuid__":"3c7e1cc0-d7da-45f2-ad34-2c7b9eb01829"}},{"__type__":"76023Ko9oJGY5KawRX5mfBE","node":{"__id__":4},"m_lblSpinButton":{"__id__":6}},{"__type__":"be9ee5/hjxDrqpMYtlCdzg/","node":{"__id__":4},"transition":3,"zoomScale":1.1,"_N$target":{"__id__":4}}],"_prefab":{"__type__":"cc.PrefabInfo","root":{"__id__":1},"asset":{"__uuid__":"2a9e77e9-5d90-4ae6-9186-44fcaaacb961"},"fileId":"bb7b9p/ZKJBq7pV32pcuTcW"}},{"__type__":"cc.Node","_name":"Label","_parent":{"__id__":4},"_contentSize":{"__type__":"cc.Size","width":164,"height":129},"_position":{"__type__":"cc.Vec2","y":38},"_components":[{"__id__":6}],"_prefab":{"__type__":"cc.PrefabInfo","root":{"__id__":1},"asset":{"__uuid__":"2a9e77e9-5d90-4ae6-9186-44fcaaacb961"},"fileId":"878726BihdIBJ/1CogjlRoh"}},{"__type__":"cc.Label","node":{"__id__":5},"_useOriginalSize":false,"_actualFontSize":60,"_fontSize":70,"_enableWrapText":false,"_N$file":{"__uuid__":"89d198fc-5554-443d-9c9d-13b7868ff545"},"_isSystemFontUsed":false,"_N$string":"Running","_N$horizontalAlign":1,"_N$verticalAlign":1,"_N$overflow":2},{"__type__":"cc.Node","_name":"m_pParentNode","_parent":{"__id__":3},"_prefab":{"__type__":"cc.PrefabInfo","root":{"__id__":1},"asset":{"__uuid__":"2a9e77e9-5d90-4ae6-9186-44fcaaacb961"},"fileId":"bbe7e7i24RFGrx7PpJ2S6zC"}},{"__type__":"cc.Node","_name":"Front","_parent":{"__id__":3},"_children":[{"__id__":9}],"_components":[{"__type__":"62f433tvN1NF6zvASAxsswI","node":{"__id__":8},"m_RootObj":{"__id__":9},"m_InverseBehaviour":true}],"_prefab":{"__type__":"cc.PrefabInfo","root":{"__id__":1},"asset":{"__uuid__":"2a9e77e9-5d90-4ae6-9186-44fcaaacb961"},"fileId":"b95759XJnNCppDvmdhNlOfI"}},{"__type__":"cc.Node","_name":"sprite_trail","_parent":{"__id__":8},"_contentSize":{"__type__":"cc.Size","width":786.6666667,"height":282.6666667},"_position":{"__type__":"cc.Vec2","x":339.4,"y":457},"_components":[{"__type__":"cc.Sprite","node":{"__id__":9},"_spriteFrame":{"__uuid__":"b3bc0429-328c-43f2-ba34-3039fa62e4f7"},"_sizeMode":0,"_isTrimmedMode":false}],"_prefab":{"__type__":"cc.PrefabInfo","root":{"__id__":1},"asset":{"__uuid__":"2a9e77e9-5d90-4ae6-9186-44fcaaacb961"},"fileId":"3e194SzWnlNSblK8gj8p7sv"}},{"__type__":"cc.Node","_name":"Effects","_parent":{"__id__":3},"_children":[{"__id__":11},{"__id__":12}],"_scaleX":1.5037594,"_scaleY":1.5037594,"_components":[{"__type__":"1a518qRJ9NK4JTgREWYGhY6","node":{"__id__":10},"ExplodeTime":0.2,"ExplodeToScale":7,"ExplodeParticle":{"__id__":11}},{"__type__":"1a518qRJ9NK4JTgREWYGhY6","node":{"__id__":10},"ReversedScale":true,"ExplodeTime":0.9,"ExplodeToScale":7,"ExplodeParticle":{"__id__":12}}],"_prefab":{"__type__":"cc.PrefabInfo","root":{"__id__":1},"asset":{"__uuid__":"2a9e77e9-5d90-4ae6-9186-44fcaaacb961"},"fileId":"8ce79QrbAhFLYDKzlWzDpam"}},{"__type__":"cc.Node","_name":"sprite_glowcircle","_parent":{"__id__":10},"_contentSize":{"__type__":"cc.Size","width":256,"height":256},"_components":[{"__type__":"cc.Sprite","node":{"__id__":11},"_spriteFrame":{"__uuid__":"08b50bc2-ca56-4dd5-bf40-5583b4dfcda1"}}],"_prefab":{"__type__":"cc.PrefabInfo","root":{"__id__":1},"asset":{"__uuid__":"2a9e77e9-5d90-4ae6-9186-44fcaaacb961"},"fileId":"8e57chEY1FLWbiMJddtN+UY"}},{"__type__":"cc.Node","_name":"sprite_glowcircle_2","_parent":{"__id__":10},"_contentSize":{"__type__":"cc.Size","width":256,"height":256},"_components":[{"__type__":"cc.Sprite","node":{"__id__":12},"_spriteFrame":{"__uuid__":"08b50bc2-ca56-4dd5-bf40-5583b4dfcda1"}}],"_prefab":{"__type__":"cc.PrefabInfo","root":{"__id__":1},"asset":{"__uuid__":"2a9e77e9-5d90-4ae6-9186-44fcaaacb961"},"fileId":"b8bcd8NB1FJnK1k2hoYY8h7"}},{"__type__":"cc.Node","_name":"Components","_parent":{"__id__":2},"_children":[{"__id__":14},{"__id__":15},{"__id__":16},{"__id__":17},{"__id__":18},{"__id__":19},{"__id__":21},{"__id__":22},{"__id__":23},{"__id__":24},{"__id__":26},{"__id__":27}],"_position":{"__type__":"cc.Vec2","x":39,"y":-305},"_prefab":{"__type__":"cc.PrefabInfo","root":{"__id__":1},"asset":{"__uuid__":"2a9e77e9-5d90-4ae6-9186-44fcaaacb961"},"fileId":"bceb68t9eBKg4JIAhJn50n4"}},{"__type__":"cc.Node","_name":"sprite_bg_backslots_roulette","_parent":{"__id__":13},"_contentSize":{"__type__":"cc.Size","width":173,"height":91},"_position":{"__type__":"cc.Vec2","x":-831,"y":2105},"_components":[{"__type__":"cc.Sprite","node":{"__id__":14}}],"_prefab":{"__type__":"cc.PrefabInfo","root":{"__id__":1},"asset":{"__uuid__":"2a9e77e9-5d90-4ae6-9186-44fcaaacb961"},"fileId":"7e4fdu4yHRGRpdUZ5t7RDKx"}},{"__type__":"cc.Node","_name":"m_spriteBallShadow","_parent":{"__id__":13},"_contentSize":{"__type__":"cc.Size","width":62,"height":62},"_position":{"__type__":"cc.Vec2","x":-35,"y":-800},"_components":[{"__type__":"a87268oITdMjrbI6NegYP+t","node":{"__id__":15},"_spriteFrame":{"__uuid__":"69244ca5-f472-477a-8df0-f1e6840dbb15"},"_sizeMode":0,"_isTrimmedMode":false,"m_pEnabled":{"__uuid__":"440e46da-445f-4903-b70b-10a388278d97"},"m_sType":"String"}],"_prefab":{"__type__":"cc.PrefabInfo","root":{"__id__":1},"asset":{"__uuid__":"2a9e77e9-5d90-4ae6-9186-44fcaaacb961"},"fileId":"ea4a9H754VI2Ys43Pa3E6zH"}},{"__type__":"cc.Node","_name":"m_spriteBall","_parent":{"__id__":13},"_contentSize":{"__type__":"cc.Size","width":62,"height":62},"_position":{"__type__":"cc.Vec2","x":-113.2,"y":-800},"_components":[{"__type__":"a87268oITdMjrbI6NegYP+t","node":{"__id__":16},"_spriteFrame":{"__uuid__":"440e46da-445f-4903-b70b-10a388278d97"},"_sizeMode":0,"_isTrimmedMode":false,"m_pEnabled":{"__uuid__":"440e46da-445f-4903-b70b-10a388278d97"},"m_sType":"String"}],"_prefab":{"__type__":"cc.PrefabInfo","root":{"__id__":1},"asset":{"__uuid__":"2a9e77e9-5d90-4ae6-9186-44fcaaacb961"},"fileId":"49bb6pR751F0ZHxvBcBkCbY"}},{"__type__":"cc.Node","_name":"m_spriteBumper","_parent":{"__id__":13},"_contentSize":{"__type__":"cc.Size","width":160,"height":160},"_position":{"__type__":"cc.Vec2","x":-446,"y":-371},"_components":[{"__type__":"a87268oITdMjrbI6NegYP+t","node":{"__id__":17},"_spriteFrame":{"__uuid__":"299f339b-2286-4b70-a10b-3baeb328a93f"},"_isTrimmedMode":false,"m_vSprites":[{"__uuid__":"299f339b-2286-4b70-a10b-3baeb328a93f"}],"m_dSprites":{"sprite_bumper1_off":{"__uuid__":"299f339b-2286-4b70-a10b-3baeb328a93f"}},"m_sType":"String"}],"_prefab":{"__type__":"cc.PrefabInfo","root":{"__id__":1},"asset":{"__uuid__":"2a9e77e9-5d90-4ae6-9186-44fcaaacb961"},"fileId":"af144fcAzVCr7zPmzYDkiTT"}},{"__type__":"cc.Node","_name":"ToggledPin","_parent":{"__id__":13},"_contentSize":{"__type__":"cc.Size","width":200,"height":200},"_position":{"__type__":"cc.Vec2","x":599,"y":-716},"_components":[{"__type__":"a87268oITdMjrbI6NegYP+t","node":{"__id__":18},"_sizeMode":0,"_isTrimmedMode":false,"m_pEnabled":{"__uuid__":"4b526411-f4d4-407d-848e-f6d934ce1c82"},"m_pDisabled":{"__uuid__":"fde1c2c1-39fe-46d8-8456-a37ba9d6724a"},"m_vSprites":[{"__uuid__":"30e5ec6e-fb80-4928-b1a9-754b4db956d5"},{"__uuid__":"51041aae-a099-474d-8325-e9080600ac27"},{"__uuid__":"1811be03-a61a-474a-8e2e-c44c77cf78a6"},{"__uuid__":"0ba611a2-0d0d-4e3b-adb9-e3c600912c2e"},{"__uuid__":"f943d2c8-6564-4b1c-b093-c38ac01da490"},{"__uuid__":"bb766245-eeda-4009-8f70-c4e939472246"},{"__uuid__":"dcb72dd3-8870-472e-af54-c7f3fd8545bb"},{"__uuid__":"21af662a-792d-4eb2-b39d-2e76027cab3f"}],"m_dSprites":{"sprite_peg_big1_off":{"__uuid__":"30e5ec6e-fb80-4928-b1a9-754b4db956d5"},"sprite_peg_big2_off":{"__uuid__":"51041aae-a099-474d-8325-e9080600ac27"},"sprite_peg_big2_on":{"__uuid__":"1811be03-a61a-474a-8e2e-c44c77cf78a6"},"sprite_peg_big3_off":{"__uuid__":"0ba611a2-0d0d-4e3b-adb9-e3c600912c2e"},"sprite_peg_big3_on":{"__uuid__":"f943d2c8-6564-4b1c-b093-c38ac01da490"},"sprite_peg_big4_off":{"__uuid__":"bb766245-eeda-4009-8f70-c4e939472246"},"sprite_peg_big4_on":{"__uuid__":"dcb72dd3-8870-472e-af54-c7f3fd8545bb"},"sprite_peg_big1_noshadow":{"__uuid__":"21af662a-792d-4eb2-b39d-2e76027cab3f"}},"m_sType":"String"}],"_prefab":{"__type__":"cc.PrefabInfo","root":{"__id__":1},"asset":{"__uuid__":"2a9e77e9-5d90-4ae6-9186-44fcaaacb961"},"fileId":"a48666JvHNNh59V2MZf5uOg"}},{"__type__":"cc.Node","_name":"m_spriteRoulette","_parent":{"__id__":13},"_anchorPoint":{"__type__":"cc.Vec2","x":0.5},"_contentSize":{"__type__":"cc.Size","width":163,"height":83},"_children":[{"__id__":20}],"_position":{"__type__":"cc.Vec2","x":-29,"y":-477},"_components":[{"__type__":"cc.Sprite","node":{"__id__":19},"_sizeMode":0,"_isTrimmedMode":false}],"_prefab":{"__type__":"cc.PrefabInfo","root":{"__id__":1},"asset":{"__uuid__":"2a9e77e9-5d90-4ae6-9186-44fcaaacb961"},"fileId":"88daaZ92uhPaIhU5f2XJxqi"}},{"__type__":"cc.Node","_name":"BtnSlot","_parent":{"__id__":19},"_anchorPoint":{"__type__":"cc.Vec2","x":0.5},"_contentSize":{"__type__":"cc.Size","width":136.7,"height":109.3},"_components":[{"__type__":"be9ee5/hjxDrqpMYtlCdzg/","node":{"__id__":20},"pressedColor":{"__type__":"cc.Color","r":255,"g":255,"b":255},"_N$normalColor":{"__type__":"cc.Color","r":255,"g":255,"b":255},"_N$disabledColor":{"__type__":"cc.Color","r":255,"g":255,"b":255},"_N$target":{"__id__":20}}],"_prefab":{"__type__":"cc.PrefabInfo","root":{"__id__":1},"asset":{"__uuid__":"2a9e77e9-5d90-4ae6-9186-44fcaaacb961"},"fileId":"afb158DhlFC/rzL3wRB4OEe"}},{"__type__":"cc.Node","_name":"sprite_middle_roulette","_parent":{"__id__":13},"_contentSize":{"__type__":"cc.Size","width":531,"height":524},"_position":{"__type__":"cc.Vec2","x":-1286,"y":25},"_components":[{"__type__":"cc.Sprite","node":{"__id__":21},"_spriteFrame":{"__uuid__":"9e578931-e2e2-4887-a51c-de04f2cd07b7"}}],"_prefab":{"__type__":"cc.PrefabInfo","root":{"__id__":1},"asset":{"__uuid__":"2a9e77e9-5d90-4ae6-9186-44fcaaacb961"},"fileId":"35a18c1lgxNLIgHLv5ii+S6"}},{"__type__":"cc.Node","_name":"sprite_center_roulette","_parent":{"__id__":13},"_contentSize":{"__type__":"cc.Size","width":278,"height":278},"_position":{"__type__":"cc.Vec2","x":340,"y":-230},"_components":[{"__type__":"cc.Sprite","node":{"__id__":22},"_spriteFrame":{"__uuid__":"2fb7ca87-5607-4f72-b28b-9bce65e073b6"}}],"_prefab":{"__type__":"cc.PrefabInfo","root":{"__id__":1},"asset":{"__uuid__":"2a9e77e9-5d90-4ae6-9186-44fcaaacb961"},"fileId":"7760bKFOaRFUIEq/2ajNDzz"}},{"__type__":"cc.Node","_name":"sprite_border_roulette_mega","_parent":{"__id__":13},"_contentSize":{"__type__":"cc.Size","width":756,"height":757},"_position":{"__type__":"cc.Vec2","x":394,"y":-1120},"_components":[{"__type__":"cc.Sprite","node":{"__id__":23},"_spriteFrame":{"__uuid__":"38af286b-7ab5-47bc-980a-19ed0673e67a"}}],"_prefab":{"__type__":"cc.PrefabInfo","root":{"__id__":1},"asset":{"__uuid__":"2a9e77e9-5d90-4ae6-9186-44fcaaacb961"},"fileId":"9e1e7+ePuVMyIhtuoY8V1sp"}},{"__type__":"cc.Node","_name":"Light","_parent":{"__id__":13},"_contentSize":{"__type__":"cc.Size","width":44,"height":45},"_children":[{"__id__":25}],"_position":{"__type__":"cc.Vec2","x":-521,"y":-640},"_active":false,"_components":[{"__type__":"0eef0Bi2X9LZYSjBAk3CiQo","node":{"__id__":24},"_spriteFrame":{"__uuid__":"b343649d-2f3f-4186-9433-7d6143931449"},"m_pEnabled":{"__uuid__":"b343649d-2f3f-4186-9433-7d6143931449"},"m_vSprites":[{"__uuid__":"b343649d-2f3f-4186-9433-7d6143931449"}],"m_dSprites":{"sprite_light_on":{"__uuid__":"b343649d-2f3f-4186-9433-7d6143931449"}},"m_pShadowLight":{"__id__":25}}],"_prefab":{"__type__":"cc.PrefabInfo","root":{"__id__":1},"asset":{"__uuid__":"2a9e77e9-5d90-4ae6-9186-44fcaaacb961"},"fileId":"2b8bdij94RIsIAH1CQsGjn1"}},{"__type__":"cc.Node","_name":"sprite_backlight_wheel","_parent":{"__id__":24},"_contentSize":{"__type__":"cc.Size","width":44,"height":45},"_position":{"__type__":"cc.Vec2","y":-30},"_components":[{"__type__":"cc.Sprite","node":{"__id__":25}}],"_prefab":{"__type__":"cc.PrefabInfo","root":{"__id__":1},"asset":{"__uuid__":"2a9e77e9-5d90-4ae6-9186-44fcaaacb961"},"fileId":"9d85dSSZ7NGmKDPKSxh1kgY"}},{"__type__":"cc.Node","_name":"Light2","_parent":{"__id__":13},"_contentSize":{"__type__":"cc.Size","width":44,"height":45},"_position":{"__type__":"cc.Vec2","x":-435.9,"y":-640},"_components":[{"__type__":"0eef0Bi2X9LZYSjBAk3CiQo","node":{"__id__":26},"_spriteFrame":{"__uuid__":"b343649d-2f3f-4186-9433-7d6143931449"},"m_pEnabled":{"__uuid__":"b343649d-2f3f-4186-9433-7d6143931449"},"m_vSprites":[{"__uuid__":"b343649d-2f3f-4186-9433-7d6143931449"},{"__uuid__":"586da932-3fb8-41a0-b709-3bb53f678a03"}],"m_dSprites":{"sprite_light_on":{"__uuid__":"b343649d-2f3f-4186-9433-7d6143931449"},"sprite_light_off":{"__uuid__":"586da932-3fb8-41a0-b709-3bb53f678a03"}}}],"_prefab":{"__type__":"cc.PrefabInfo","root":{"__id__":1},"asset":{"__uuid__":"2a9e77e9-5d90-4ae6-9186-44fcaaacb961"},"fileId":"0c773MOBhFLzJyO6bYK4+Py"}},{"__type__":"cc.Node","_name":"sprite_ground_light_on","_parent":{"__id__":13},"_contentSize":{"__type__":"cc.Size","width":51,"height":51},"_position":{"__type__":"cc.Vec2","y":-466},"_components":[{"__type__":"cc.Sprite","node":{"__id__":27},"_spriteFrame":{"__uuid__":"00ffea9d-2e29-495b-802d-568860977123"}}],"_prefab":{"__type__":"cc.PrefabInfo","root":{"__id__":1},"asset":{"__uuid__":"2a9e77e9-5d90-4ae6-9186-44fcaaacb961"},"fileId":"f1a82+WRU1HUZv2+rpy3XKM"}},{"__type__":"b6182bu1+BLUZ6g1ZOCe/Gr","node":{"__id__":2},"_enabled":false,"m_pScene":{"__id__":3},"m_sGameMode":"BigJackpot","m_pParentNode":{"__id__":7},"m_spriteBall":{"__id__":16},"m_spriteBumper":{"__id__":17},"m_spriteToggledPin":{"__id__":18},"m_spriteRoulette":{"__id__":19},"m_lblSpinButton":{"__id__":6}}]