[[{"__type__":"cc.Prefab","_name":"UITutorialSlideShow_BigJackpot","data":{"__id__":1}},{"__type__":"cc.Node","_name":"UITutorialSlideShow_BigJackpot","_color":{"__type__":"cc.Color","r":167,"g":167,"b":167},"_contentSize":{"__type__":"cc.Size","width":720,"height":1280},"_children":[{"__id__":2},{"__id__":3}],"_components":[{"__type__":"cc.Layout","node":{"__id__":1},"_layoutSize":{"__type__":"cc.Size","width":720,"height":1280}},{"__type__":"7c9183Ci3JAkLFsHc8jvuKT","node":{"__id__":1},"SlideShowList":[{"__id__":4}]}],"_prefab":{"__type__":"cc.PrefabInfo","root":{"__id__":1},"asset":{"__uuid__":"36d9e433-5f0b-4a9f-bb0c-17433424d190"},"fileId":"7484bicX3NFN4DR1DdFfb2i"}},{"__type__":"cc.Node","_name":"BGSprite","_opacity":137,"_color":{"__type__":"cc.Color"},"_parent":{"__id__":1},"_contentSize":{"__type__":"cc.Size","width":2142,"height":2602},"_components":[{"__type__":"cc.Sprite","node":{"__id__":2},"_spriteFrame":{"__uuid__":"591432ae-559c-47f4-b606-33ccb3f7929e"},"_sizeMode":0},{"__type__":"cc.Button","node":{"__id__":2},"_N$target":{"__id__":2}}],"_prefab":{"__type__":"cc.PrefabInfo","root":{"__id__":1},"asset":{"__uuid__":"36d9e433-5f0b-4a9f-bb0c-17433424d190"},"fileId":"24365RVy6ZFJY2HChg6kYrc"}},{"__type__":"cc.Node","_name":"SlideShow","_parent":{"__id__":1},"_children":[{"__id__":4}],"_prefab":{"__type__":"cc.PrefabInfo","root":{"__id__":1},"asset":{"__uuid__":"36d9e433-5f0b-4a9f-bb0c-17433424d190"},"fileId":"e74f80XZTdP95sacrIlh2+c"}},{"__type__":"cc.Node","_name":"Tut1","_parent":{"__id__":3},"_contentSize":{"__type__":"cc.Size","width":720,"height":1280},"_children":[{"__id__":5},{"__id__":6},{"__id__":7},{"__id__":8},{"__id__":9}],"_components":[{"__type__":"cc.Sprite","node":{"__id__":4},"_spriteFrame":{"__uuid__":"8eedc2b8-919e-448c-a81f-6f8e9391370a"}}],"_prefab":{"__type__":"cc.PrefabInfo","root":{"__id__":1},"asset":{"__uuid__":"36d9e433-5f0b-4a9f-bb0c-17433424d190"},"fileId":"e7f1e2ovyBPOLi31K13nA7I"}},{"__type__":"cc.Node","_name":"Button","_parent":{"__id__":4},"_contentSize":{"__type__":"cc.Size","width":720,"height":1280},"_components":[{"__type__":"be9ee5/hjxDrqpMYtlCdzg/","node":{"__id__":5},"zoomScale":1.1,"clickEvents":[{"__type__":"cc.ClickEvent","target":{"__id__":1},"component":"UITutorialSlideShow","handler":"onClickNext"}],"_N$target":{"__id__":5}}],"_prefab":{"__type__":"cc.PrefabInfo","root":{"__id__":1},"asset":{"__uuid__":"36d9e433-5f0b-4a9f-bb0c-17433424d190"},"fileId":"bb019Agx0ZHDZ78931VvhWS"}},{"__type__":"cc.Node","_name":"1.Description","_parent":{"__id__":4},"_contentSize":{"__type__":"cc.Size","width":498,"height":71},"_position":{"__type__":"cc.Vec2","x":90,"y":-444},"_components":[{"__type__":"b609eqLkLREEI4uiDRFDHL9","node":{"__id__":6},"_useOriginalSize":false,"_actualFontSize":26,"_fontSize":35,"_N$file":{"__uuid__":"f6bc82b5-ada9-4aea-a7d5-5674e3b582aa"},"_isSystemFontUsed":false,"_N$horizontalAlign":1,"_N$verticalAlign":1,"_N$overflow":2,"m_sText":"To help you, you can always use cards in order to improve you chances","_N$textKey":"95"}],"_prefab":{"__type__":"cc.PrefabInfo","root":{"__id__":1},"asset":{"__uuid__":"36d9e433-5f0b-4a9f-bb0c-17433424d190"},"fileId":"47decJxJLFMQ7bUdJhDAwOt"}},{"__type__":"cc.Node","_name":"2.Description","_parent":{"__id__":4},"_contentSize":{"__type__":"cc.Size","width":470.4,"height":94},"_position":{"__type__":"cc.Vec2","x":-55.8,"y":-273.7},"_active":false,"_components":[{"__type__":"b609eqLkLREEI4uiDRFDHL9","node":{"__id__":7},"_useOriginalSize":false,"_actualFontSize":27,"_fontSize":35,"_N$file":{"__uuid__":"f6bc82b5-ada9-4aea-a7d5-5674e3b582aa"},"_isSystemFontUsed":false,"_N$horizontalAlign":1,"_N$verticalAlign":1,"_N$overflow":2,"m_sText":"To help you, you can always use cards in order to improve you chances","_N$textKey":"95"}],"_prefab":{"__type__":"cc.PrefabInfo","root":{"__id__":1},"asset":{"__uuid__":"36d9e433-5f0b-4a9f-bb0c-17433424d190"},"fileId":"47decJxJLFMQ7bUdJhDAwOt"}},{"__type__":"cc.Node","_name":"3.Description","_parent":{"__id__":4},"_contentSize":{"__type__":"cc.Size","width":498,"height":120},"_position":{"__type__":"cc.Vec2","x":-72,"y":-97},"_components":[{"__type__":"b609eqLkLREEI4uiDRFDHL9","node":{"__id__":8},"_useOriginalSize":false,"_actualFontSize":35,"_fontSize":35,"_N$file":{"__uuid__":"f6bc82b5-ada9-4aea-a7d5-5674e3b582aa"},"_isSystemFontUsed":false,"_N$horizontalAlign":1,"_N$verticalAlign":1,"_N$overflow":2,"m_sText":"Cards used are consumed however new cards can be used every round","_N$textKey":"96"}],"_prefab":{"__type__":"cc.PrefabInfo","root":{"__id__":1},"asset":{"__uuid__":"36d9e433-5f0b-4a9f-bb0c-17433424d190"},"fileId":"47decJxJLFMQ7bUdJhDAwOt"}},{"__type__":"cc.Node","_name":"4.Description","_parent":{"__id__":4},"_contentSize":{"__type__":"cc.Size","width":498,"height":145.4},"_position":{"__type__":"cc.Vec2","x":11,"y":247},"_components":[{"__type__":"b609eqLkLREEI4uiDRFDHL9","node":{"__id__":9},"_useOriginalSize":false,"_actualFontSize":35,"_fontSize":35,"_N$file":{"__uuid__":"f6bc82b5-ada9-4aea-a7d5-5674e3b582aa"},"_isSystemFontUsed":false,"_N$horizontalAlign":1,"_N$verticalAlign":1,"_N$overflow":2,"m_sText":"To win the MEGA Jackpot, you have to beat 3 rounds in a row.","_N$textKey":"92"}],"_prefab":{"__type__":"cc.PrefabInfo","root":{"__id__":1},"asset":{"__uuid__":"36d9e433-5f0b-4a9f-bb0c-17433424d190"},"fileId":"47decJxJLFMQ7bUdJhDAwOt"}}],{"__type__":"cc.SpriteFrame","content":{"name":"Tutorial_Mega_Step01","texture":"4a324fb2-10e1-4468-88aa-bf20a076713d","rect":[0,0,720,1280],"offset":[0,0],"originalSize":[720,1280]}}]